{"id": 2232063666642234505, "timestamp": "2003-04-06 02:00", "home_team": "巴斯蒂", "away_team": "特鲁瓦", "ouzhi": [{"company": "伟德", "europe_odds": ["1.60000", "3.25000", "5.00000", "0.55180", "0.27160", "0.17660", "0.88290", "0.88290", "0.88290", "0.88290"]}], "yapan": [{"company": "澳门", "asia_handicap": [0.95, "半球/一球", 0.9]}], "score": [1, 1], "result": 0, "input_oupei_avg": ["1.60000", "3.25000", "5.00000", "0.55180", "0.27160", "0.17660", "0.88290", "0.88000", "0.88000", "0.88000"], "input_discrete": ["0.0", "0.0", "0"]}